[
  {
    "Name": "Bulldog inglés",
    "Location": "Inglaterra",
    "Details": "Baboons are African and Arabian Old World monkeys belonging to the genus Papio, part of the subfamily Cercopithecinae.",
    "Image": "https://www.dogalize.com/wp-content/uploads/2017/01/animal-1484845_960_720.jpg",
    "Population": 10000,
    "Latitude": -8.783195,
    "Longitude": 34.508523
  },
  {
    "Name": "Chow chow",
    "Location": "China",
    "Details": "The capuchin monkeys are New World monkeys of the subfamily Cebinae. Prior to 2011, the subfamily contained only a single genus, Cebus.",
    "Image": "https://www.dogalize.com/wp-content/uploads/2016/12/ChowChow_hero.jpg",
    "Population": 23000,
    "Latitude": 12.769013,
    "Longitude": -85.602364
  },
  {
    "Name": "Collie",
    "Location": "Escocia",
    "Details": "The blue monkey or diademed monkey is a species of Old World monkey native to Central and East Africa, ranging from the upper Congo River basin east to the East African Rift and south to northern Angola and Zambia",
    "Image": "https://www.dogalize.com/wp-content/uploads/2017/01/C3.jpg",
    "Population": 12000,
    "Latitude": 1.957709,
    "Longitude": 37.297204
  },
  {
    "Name": "Dalmata",
    "Location": "Croacia",
    "Details": "The squirrel monkeys are the New World monkeys of the genus Saimiri. They are the only genus in the subfamily Saimirinae. The name of the genus Saimiri is of Tupi origin, and was also used as an English name by early researchers.",
    "Image": "https://www.dogalize.com/wp-content/uploads/2016/12/25_shutterstock_26182564.jpg",
    "Population": 11000,
    "Latitude": -8.783195,
    "Longitude": -55.491477
  },
  {
    "Name": "Labrador",
    "Location": "Cnada",
    "Details": "The golden lion tamarin also known as the golden marmoset, is a small New World monkey of the family Callitrichidae.",
    "Image": "https://www.dogalize.com/wp-content/uploads/2017/01/dog-1210559_960_720.jpg",
    "Population": 19000,
    "Latitude": -14.235004,
    "Longitude": -51.92528
  },
  {
    "Name": "Matin Napolitano",
    "Location": "Roma",
    "Details": "Howler monkeys are among the largest of the New World monkeys. Fifteen species are currently recognised. Previously classified in the family Cebidae, they are now placed in the family Atelidae.",
    "Image": "https://www.dogalize.com/wp-content/uploads/2017/01/eQ8Iugqr.png",
    "Population": 8000,
    "Latitude": -8.783195,
    "Longitude": -55.491477
  },
  {
    "Name": "Pastor suizo",
    "Location": "Suiza",
    "Details": "The Japanese macaque, is a terrestrial Old World monkey species native to Japan. They are also sometimes known as the snow monkey because they live in areas where snow covers the ground for months each",
    "Image": "https://www.dogalize.com/wp-content/uploads/2017/02/perro-pastor-blanco-suizo-.jpg",
    "Population": 1000,
    "Latitude": 36.204824,
    "Longitude": 138.252924
  },
  {
    "Name": "Poodle",
    "Location": "Francia, Rusia y Alemania",
    "Details": "The mandrill is a primate of the Old World monkey family, closely related to the baboons and even more closely to the drill. It is found in southern Cameroon, Gabon, Equatorial Guinea, and Congo.",
    "Image": "https://www.dogalize.com/wp-content/uploads/2016/11/perro-poodle-adoptar-un-poodle-juego-socializacion.jpg",
    "Population": 17000,
    "Latitude": 7.369722,
    "Longitude": 12.354722
  },
  {
    "Name": "San Bernardo",
    "Location": "Norte de Italia",
    "Details": "The proboscis monkey or long-nosed monkey, known as the bekantan in Malay, is a reddish-brown arboreal Old World monkey that is endemic to the south-east Asian island of Borneo.",
    "Image": "https://www.dogalize.com/wp-content/uploads/2017/01/dog-1905916_960_720.jpg",
    "Population": 15000,
    "Latitude": 0.961883,
    "Longitude": 114.55485
  },
  {
    "Name": "Xolo",
    "Location": "Mexico",
    "Details": "This little trouble maker lives in Seattle with James and loves traveling on adventures with James and tweeting @MotzMonkeys. He by far is an Android fanboy and is getting ready for the new Nexus 6P!",
    "Image": "https://www.dogalize.com/wp-content/uploads/2017/02/xoloitzcuintle-4.jpg",
    "Population": 1,
    "Latitude": 47.606209,
    "Longitude": -122.332071
  },
  {
    "Name": "Terranova",
    "Location": "Isla Newfoundland",
    "Details": "An adorable Monkey who is traveling the world with Heather and live tweets his adventures @MotzMonkeys. His favorite platform is iOS by far and is excited for the new iPhone Xs!",
    "Image": "https://www.dogalize.com/wp-content/uploads/2017/05/am_79226_5868111_342288.jpg",
    "Population": 1,
    "Latitude": 33.448377,
    "Longitude": -112.074037
  },
  {
    "Name": "Whipped",
    "Location": "Inglaterra",
    "Details": "The red-shanked douc is a species of Old World monkey, among the most colourful of all primates. The douc is an arboreal and diurnal monkey that eats and sleeps in the trees of the forest.",
    "Image": "https://www.dogalize.com/wp-content/uploads/2017/05/Whippet3-800x400.jpg",
    "Population": 1300,
    "Latitude": 16.111648,
    "Longitude": 108.262122
  },
  {
    "Name": "Sussex",
    "Location": "Inglaterra",
    "Details": "An adorable Monkey who is traveling the world with Heather and live tweets his adventures @MotzMonkeys. His favorite platform is iOS by far and is excited for the new iPhone 6s!",
    "Image": "https://www.dogalize.com/wp-content/uploads/2017/05/Sussex_Spaniel.jpg",
    "Population": 1,
    "Latitude": 47.608013,
    "Longitude": -122.335167
  }
]